customcolor/__init__.py
customcolor/result.py
customcolor/runner.py
customcolor/colors/__init__.py
customcolor/colors/_linux_color_types.py
customcolor/colors/_linux_console_utils.py
customcolor/colors/_win_color_types.py
customcolor/colors/_win_console_utils.py
customcolor/colors/color_print.py
customcolor-0.0.4.dist-info/LICENSE
customcolor-0.0.4.dist-info/METADATA
customcolor-0.0.4.dist-info/WHEEL
customcolor-0.0.4.dist-info/top_level.txt
customcolor-0.0.4.dist-info/RECORD
