Metadata-Version: 2.1
Name: customcolor
Version: 0.0.4
Summary: Library for colored output of unit tests in the console
Home-page: https://github.com/gimpelgit/customcolor/
Author: Kirill
Author-email: gimpelcomp@gmail.com
License: MIT
Keywords: unittest colour color output print windows linux text-decoration
Classifier: Programming Language :: Python
Classifier: Programming Language :: Python :: 3
Classifier: Programming Language :: Python :: 3.6
Requires-Python: >=3.6
License-File: LICENSE
